Workbook
Name Aporte: 'SIMULADOR APORTE'!$D$17
Name Aporte: SIMULADOR!$D$12
Name Patrimonio: 'SIMULADOR APORTE'!$D$20
Name Patrimonio: SIMULADOR!$D$15
Name Qtd_anos: 'SIMULADOR APORTE'!$D$18
Name Qtd_anos: SIMULADOR!$D$13
Name Rendimento: 'SIMULADOR APORTE'!$D$13
Name Rendimento: SIMULADOR!$H$13
Name rendimento_carteira: 'SIMULADOR APORTE'!$D$17
Name rendimento_carteira: SIMULADOR!$D$12
Name Taxa_mensal: 'SIMULADOR APORTE'!$D$19
Name Taxa_mensal: SIMULADOR!$D$14

Sheet SIMULADOR
B11: INVESTIMENTO MENSAL | F11: CONFIGURAÇÕES
B12: Quanto investir por mês ? | D12: 250 | F12: Salário | H12: 2000
B13: Por Quantos Anos ? | D13: 5 | F13: Rendimento Carteira | H13: 0.006
B14: Taxa de Rendimento mensal ? | D14: 0.01079 | F14: Sugestão de Investimento (30%) | H14: =H12*30% -> 600
B15: Patrimônio acumulado ? | D15: =FV(Taxa_mensal,Qtd_anos*12,Aporte*-1) -> 20944.228
B16: Dividendos Mensais ? | D16: =$D$15*$H$13 -> 125.66537
B18: Cenários | D18: Dividendo
A19: 2 | B19: Quanto em 2 Anos ? | C19: =FV($D$14,$A19*12,rendimento_carteira*-1) -> 6806.9068 | D19: =C19*Rendimento -> 40.841441
A20: 5 | B20: Quanto em 5 Anos ? | C20: =FV($D$14,$A20*12,rendimento_carteira*-1) -> 20944.228 | D20: =C20*Rendimento -> 125.66537
A21: 10 | B21: Quanto em 10 Anos ? | C21: =FV($D$14,$A21*12,rendimento_carteira*-1) -> 60821.053 | D21: =C21*Rendimento -> 364.92632
A22: 20 | B22: Quanto em 20 Anos ? | C22: =FV($D$14,$A22*12,rendimento_carteira*-1) -> 281299.6 | D22: =C22*Rendimento -> 1687.7976
A23: 30 | B23: Quanto em 30 Anos ? | C23: =FV($D$14,$A23*12,rendimento_carteira*-1) -> 1080542.4 | D23: =C23*Rendimento -> 6483.2545
B26: PERFIL | C26: Conservador
B27: VALOR A SER INVESTIDO MENSALMENTE | C27: =Aporte -> 250
B29: TIPO DE FII | C29: Percentual Sugerido | D29: Valores
B30: PAPEL | C30: =VLOOKUP($C$26&"-"&B30,Planilha2!$A:$D,4,0) -> 0.3 | D30: =C30*$C$27 -> 75
B31: TIJOLO | C31: =VLOOKUP($C$26&"-"&B31,Planilha2!$A:$D,4,0) -> 0.3 | D31: =C31*$C$27 -> 75
B32: HÍBRIDOS | C32: =VLOOKUP($C$26&"-"&B32,Planilha2!$A:$D,4,0) -> 0.2 | D32: =C32*$C$27 -> 50
B33: FOFs | C33: =VLOOKUP($C$26&"-"&B33,Planilha2!$A:$D,4,0) -> 0.2 | D33: =C33*$C$27 -> 50
B34: DESENVOLVIMENTO | C34: =VLOOKUP($C$26&"-"&B34,Planilha2!$A:$D,4,0) -> 0 | D34: =C34*$C$27 -> 0
B35: HOTELARIAS | C35: =VLOOKUP($C$26&"-"&B35,Planilha2!$A:$D,4,0) -> 0 | D35: =C35*$C$27 -> 0
D36: =SUM(D30:D35) -> 250

Sheet SIMULADOR APORTE
B11: CONFIGURAÇÕES
B12: Salário | D12: 2000
B13: Rendimento Carteira | D13: 0.006
B14: Sugestão de Investimento (30%) | D14: =D12*30% -> 600
B16: INVESTIMENTO MENSAL
B17: Quanto investir por mês ? | D17: 600
B18: Por Quantos Anos ? | D18: 5
B19: Taxa de Rendimento mensal ? | D19: 0.01079
B20: Patrimônio acumulado ? | D20: =FV(Taxa_mensal,Qtd_anos*12,Aporte*-1) -> 50266.148
B21: Dividendos Mensais ? | D21: =$D$20*$D$13 -> 301.59689
B23: Cenários | D23: Dividendo
A24: 2 | B24: Quanto em 2 Anos ? | C24: =FV($D$19,$A24*12,rendimento_carteira*-1) -> 16336.576 | D24: =C24*Rendimento -> 98.019458
A25: 5 | B25: Quanto em 5 Anos ? | C25: =FV($D$19,$A25*12,rendimento_carteira*-1) -> 50266.148 | D25: =C25*Rendimento -> 301.59689
A26: 10 | B26: Quanto em 10 Anos ? | C26: =FV($D$19,$A26*12,rendimento_carteira*-1) -> 145970.53 | D26: =C26*Rendimento -> 875.82317
A27: 20 | B27: Quanto em 20 Anos ? | C27: =FV($D$19,$A27*12,rendimento_carteira*-1) -> 675119.04 | D27: =C27*Rendimento -> 4050.7142
A28: 30 | B28: Quanto em 30 Anos ? | C28: =FV($D$19,$A28*12,rendimento_carteira*-1) -> 2593301.8 | D28: =C28*Rendimento -> 15559.811
B31: PERFIL | C31: Conservador
B32: VALOR A SER INVESTIDO POR MÊS | C32: =Aporte -> 600
B34: TIPO DE FII | C34: Percentual Sugerido | D34: Valores
B35: PAPEL | C35: =VLOOKUP($C$31&"-"&B35,Planilha2!$A:$D,4,0) -> 0.3 | D35: =C35*$C$32 -> 180
B36: TIJOLO | C36: =VLOOKUP($C$31&"-"&B36,Planilha2!$A:$D,4,0) -> 0.3 | D36: =C36*$C$32 -> 180
B37: HÍBRIDOS | C37: =VLOOKUP($C$31&"-"&B37,Planilha2!$A:$D,4,0) -> 0.2 | D37: =C37*$C$32 -> 120
B38: FOFs | C38: =VLOOKUP($C$31&"-"&B38,Planilha2!$A:$D,4,0) -> 0.2 | D38: =C38*$C$32 -> 120
B39: DESENVOLVIMENTO | C39: =VLOOKUP($C$31&"-"&B39,Planilha2!$A:$D,4,0) -> 0 | D39: =C39*$C$32 -> 0
B40: HOTELARIAS | C40: =VLOOKUP($C$31&"-"&B40,Planilha2!$A:$D,4,0) -> 0 | D40: =C40*$C$32 -> 0
D41: =SUM(D35:D40) -> 600

Sheet Planilha2
A1: CHAVE | B1: PERFIL | C1: TIPO DE FII | D1: %
A2: =B2&"-"&C2 -> Conservador-PAPEL | B2: Conservador | C2: PAPEL | D2: 0.3
A3: =B3&"-"&C3 -> Conservador-TIJOLO | B3: Conservador | C3: TIJOLO | D3: 0.3
A4: =B4&"-"&C4 -> Conservador-HÍBRIDOS | B4: Conservador | C4: HÍBRIDOS | D4: 0.2
A5: =B5&"-"&C5 -> Conservador-FOFs | B5: Conservador | C5: FOFs | D5: 0.2
A6: =B6&"-"&C6 -> Conservador-DESENVOLVIMENTO | B6: Conservador | C6: DESENVOLVIMENTO | D6: 0
A7: =B7&"-"&C7 -> Conservador-HOTELARIAS | B7: Conservador | C7: HOTELARIAS | D7: 0
A8: =B8&"-"&C8 -> Moderado-PAPEL | B8: Moderado | C8: PAPEL | D8: 0.3
A9: =B9&"-"&C9 -> Moderado-TIJOLO | B9: Moderado | C9: TIJOLO | D9: 0.3
A10: =B10&"-"&C10 -> Moderado-HÍBRIDOS | B10: Moderado | C10: HÍBRIDOS | D10: 0.1
A11: =B11&"-"&C11 -> Moderado-FOFs | B11: Moderado | C11: FOFs | D11: 0.1
A12: =B12&"-"&C12 -> Moderado-DESENVOLVIMENTO | B12: Moderado | C12: DESENVOLVIMENTO | D12: 0.1
A13: =B13&"-"&C13 -> Moderado-HOTELARIAS | B13: Moderado | C13: HOTELARIAS | D13: 0.1
... A19: =B19&"-"&C19 -> Agressivo-HOTELARIAS | B19: Agressivo | C19: HOTELARIAS | D19: 0.1
